fcdproc/__init__.py
fcdproc/cli.py
fcdproc/data/__files/TT_N27.nii
fcdproc/data/__files/lh.lausanne_250.annot
fcdproc/data/__files/lh.lausanne_250_ColorLUT.txt
fcdproc/data/__files/rh.lausanne_250.annot
fcdproc/data/__files/rh.lausanne_250_ColorLUT.txt
fcdproc/interfaces/FCD_preproc.py
fcdproc/interfaces/FCD_python.py
fcdproc/interfaces/__init__.py
fcdproc/utils/__init__.py
fcdproc/utils/colors.py
fcdproc/utils/misc.py
fcdproc/workflow/__init__.py
fcdproc/workflow/anatomical.py
fcdproc/workflow/base.py
fcdproc/workflow/modeling.py
fcdproc-0.4.5.dist-info/LICENSE.txt
fcdproc-0.4.5.dist-info/METADATA
fcdproc-0.4.5.dist-info/WHEEL
fcdproc-0.4.5.dist-info/entry_points.txt
fcdproc-0.4.5.dist-info/top_level.txt
fcdproc-0.4.5.dist-info/RECORD
