Metadata-Version: 2.1
Name: fcdproc
Version: 0.4.5
Summary: Python package for FCD lesion detection.
Home-page: https://github.com/ShervinAbd92/fcdproc
Author: Inati Lab, NINDS, NIH
Author-email: shervin.abd71@gmail.com
License: Public Domain
Platform: UNKNOWN
Classifier: Development Status :: 2 - Pre-Alpha
Classifier: Natural Language :: English
Classifier: Programming Language :: Python :: 3
License-File: LICENSE.txt
Requires-Dist: click
Requires-Dist: nibabel
Requires-Dist: numpy
Requires-Dist: scipy
Requires-Dist: nipype
Requires-Dist: fmriprep (>=20.2.5)
Requires-Dist: smriprep
Requires-Dist: jem
Requires-Dist: niworkflows
Requires-Dist: requests
Requires-Dist: nitransforms
Requires-Dist: reports
Requires-Dist: dotcli
Requires-Dist: matplotlib (==3.3.4)
Requires-Dist: pathlib
Requires-Dist: gitpython (>=3.0.8)
Requires-Dist: tomlkit (==0.7.0)
Requires-Dist: six (>=1.11.0)
Requires-Dist: sphinx-click
Requires-Dist: tomli (>=1.0.0)
